gmshgeometry/GeometryController.py
gmshgeometry/NearestNeighbors.py
gmshgeometry/VoronoiController.py
gmshgeometry/__init__.py
gmshgeometry-0.0.9.dist-info/METADATA
gmshgeometry-0.0.9.dist-info/WHEEL
gmshgeometry-0.0.9.dist-info/top_level.txt
gmshgeometry-0.0.9.dist-info/RECORD
